mednotegen/__init__.py
mednotegen/cli.py
mednotegen/config.py
mednotegen/generator.py
mednotegen/llm_utils.py
mednotegen/pdf_utils.py
mednotegen/synthea_integration.py
mednotegen/templates.py
mednotegen-0.1.2.dist-info/licenses/LICENSE-APACHE-2.0
mednotegen-0.1.2.dist-info/METADATA
mednotegen-0.1.2.dist-info/WHEEL
mednotegen-0.1.2.dist-info/entry_points.txt
mednotegen-0.1.2.dist-info/top_level.txt
mednotegen-0.1.2.dist-info/RECORD
