Metadata-Version: 2.4
Name: mednotegen
Version: 0.1.2
Summary: Generate fake patient reports as PDFs.
Author-email: Mikael Moise <mikael.moise@protonmail.com>
License: MIT
Project-URL: Repository, https://github.com/nortelabs/mednotegen
Project-URL: Bug Tracker, https://github.com/nortelabs/mednotegen/issues
Keywords: synthea,medical notes,pdf
Classifier: Development Status :: 5 - Production/Stable
Classifier: Programming Language :: Python
Classifier: Programming Language :: Python :: 3
Classifier: Programming Language :: Python :: 3.10
Classifier: Programming Language :: Python :: 3.11
Classifier: Programming Language :: Python :: 3.12
Classifier: Operating System :: OS Independent
Classifier: Topic :: Scientific/Engineering
Requires-Python: >=3.7
License-File: LICENSE-APACHE-2.0
Requires-Dist: faker
Requires-Dist: fpdf
Dynamic: license-file
